<annotation>
	<folder>Cars_100</folder>
	<filename>00049.jpg</filename>
	<path>/home/convo/code/dataset/Cars_100/00049.jpg</path>
	<source>
		<database>Unknown</database>
	</source>
	<size>
		<width>510</width>
		<height>387</height>
		<depth>3</depth>
	</size>
	<segmented>0</segmented>
	<object>
		<name>car</name>
		<pose>Unspecified</pose>
		<truncated>0</truncated>
		<difficult>0</difficult>
		<bndbox>
			<xmin>15</xmin>
			<ymin>135</ymin>
			<xmax>483</xmax>
			<ymax>335</ymax>
		</bndbox>
	</object>
</annotation>
